ogr2osm/__init__.py
ogr2osm/__main__.py
ogr2osm/datawriter_base_class.py
ogr2osm/fileformat_pb2.py
ogr2osm/ogr2osm.py
ogr2osm/ogr_datasource.py
ogr2osm/osm_data.py
ogr2osm/osm_datawriter.py
ogr2osm/osm_geometries.py
ogr2osm/osmformat_pb2.py
ogr2osm/pbf_datawriter.py
ogr2osm/translation_base_class.py
ogr2osm/version.py
ogr2osm-1.1.1.dist-info/LICENSE
ogr2osm-1.1.1.dist-info/METADATA
ogr2osm-1.1.1.dist-info/WHEEL
ogr2osm-1.1.1.dist-info/entry_points.txt
ogr2osm-1.1.1.dist-info/top_level.txt
ogr2osm-1.1.1.dist-info/RECORD
