Metadata-Version: 2.1
Name: ogr2osm
Version: 1.1.1
Summary: A tool for converting ogr-readable files like shapefiles into .osm or .pbf data
Home-page: https://github.com/roelderickx/ogr2osm
Author: Roel Derickx
Author-email: ogr2osm.pypi@derickx.be
License: MIT License
Platform: UNKNOWN
Classifier: Environment :: Console
Classifier: Topic :: Scientific/Engineering :: GIS
Classifier: Development Status :: 5 - Production/Stable
Classifier: Programming Language :: Python :: 3
Classifier: License :: OSI Approved :: MIT License
Classifier: Operating System :: OS Independent
Requires-Python: >=3.7
License-File: LICENSE
Requires-Dist: lxml (>=4.3.0)
Requires-Dist: GDAL (>=3.0.0)
